solnml
