Metadata-Version: 2.1
Name: soln-ml
Version: 1.0.2
Summary: Soln-ML: Towards Self-Learning AutoML System.
Home-page: https://github.com/thomas-young-2013/soln-ml
Author: AutoML Researcher @ DAIM
Author-email: liyang.cs@pku.edu.cn
License: LICENSE.txt
Keywords: AutoML,machine learning
Platform: UNKNOWN
Requires-Python: >=3.5.*
Requires-Dist: setuptools
Requires-Dist: nose
Requires-Dist: ConfigSpace (<0.5,>=0.4.0)
Requires-Dist: Cython
Requires-Dist: pyyaml
Requires-Dist: litebo
Requires-Dist: lightgbm
Requires-Dist: pandas (>=0.24.0)
Requires-Dist: numpy (>=1.9.0)
Requires-Dist: scipy (>=0.14.1)
Requires-Dist: pyrfr (==0.8.0)
Requires-Dist: scikit-learn (==0.21.3)
Requires-Dist: imbalanced-learn (==0.5.0)
Requires-Dist: tabulate (>=0.8.5)
Requires-Dist: arff
Requires-Dist: pillow
